{"errors":[],"warnings":[],"namedChunkGroups":{"app":{"chunks":[7,3],"assets":["webpack-runtime-f55943bb93b98344b23b.js","webpack-runtime-f55943bb93b98344b23b.js.map","app-caf613e6eb677e40bf42.js","app-caf613e6eb677e40bf42.js.map"],"children":{},"childAssets":{}},"component---src-pages-404-js":{"chunks":[0,1,2,4],"assets":["styles.4c4b96d531edd0fda396.css","styles-4eeca95d46f6856f138c.js","styles-4eeca95d46f6856f138c.js.map","1-1cd05065d209a8762fa4.js","1-1cd05065d209a8762fa4.js.map","2-99d96af6076e83e6b5c8.js","2-99d96af6076e83e6b5c8.js.map","component---src-pages-404-js-ba7e042fb3d3209b7be6.js","component---src-pages-404-js-ba7e042fb3d3209b7be6.js.map"],"children":{},"childAssets":{}},"component---src-pages-index-js":{"chunks":[0,1,5],"assets":["styles.4c4b96d531edd0fda396.css","styles-4eeca95d46f6856f138c.js","styles-4eeca95d46f6856f138c.js.map","1-1cd05065d209a8762fa4.js","1-1cd05065d209a8762fa4.js.map","component---src-pages-index-js-12568f5cd52f41f35ee6.js","component---src-pages-index-js-12568f5cd52f41f35ee6.js.map"],"children":{},"childAssets":{}},"component---src-pages-page-2-js":{"chunks":[0,1,2,6],"assets":["styles.4c4b96d531edd0fda396.css","styles-4eeca95d46f6856f138c.js","styles-4eeca95d46f6856f138c.js.map","1-1cd05065d209a8762fa4.js","1-1cd05065d209a8762fa4.js.map","2-99d96af6076e83e6b5c8.js","2-99d96af6076e83e6b5c8.js.map","component---src-pages-page-2-js-50eb39b0e7c0d517e185.js","component---src-pages-page-2-js-50eb39b0e7c0d517e185.js.map"],"children":{},"childAssets":{}}},"assetsByChunkName":{"app":["webpack-runtime-f55943bb93b98344b23b.js","app-caf613e6eb677e40bf42.js"],"component---src-pages-404-js":["styles.4c4b96d531edd0fda396.css","styles-4eeca95d46f6856f138c.js","1-1cd05065d209a8762fa4.js","2-99d96af6076e83e6b5c8.js","component---src-pages-404-js-ba7e042fb3d3209b7be6.js"],"component---src-pages-index-js":["styles.4c4b96d531edd0fda396.css","styles-4eeca95d46f6856f138c.js","1-1cd05065d209a8762fa4.js","component---src-pages-index-js-12568f5cd52f41f35ee6.js"],"component---src-pages-page-2-js":["styles.4c4b96d531edd0fda396.css","styles-4eeca95d46f6856f138c.js","1-1cd05065d209a8762fa4.js","2-99d96af6076e83e6b5c8.js","component---src-pages-page-2-js-50eb39b0e7c0d517e185.js"]}}